{
    "FileVersion": "2.0.0",
    "EnableAddressable": true,
    "LocationToLower": false,
    "IncludeAssetGUID": false,
    "OutputNameStyle": 0,
    "BuildPipeline": "BuiltinBuildPipeline",
    "PackageName": "DefaultPackage",
    "PackageVersion": "Simulate",
    "AssetList": [
        {
            "Address": "buff_conditionstable",
            "AssetPath": "Assets/ArtAssets/DATAOUTPUT/buff_conditionstable.json",
            "AssetGUID": "",
            "AssetTags": [],
            "BundleID": 0
        },
        {
            "Address": "buff_passiveskillstable",
            "AssetPath": "Assets/ArtAssets/DATAOUTPUT/buff_passiveskillstable.json",
            "AssetGUID": "",
            "AssetTags": [],
            "BundleID": 0
        },
        {
            "Address": "cha_charactertable",
            "AssetPath": "Assets/ArtAssets/DATAOUTPUT/cha_charactertable.json",
            "AssetGUID": "",
            "AssetTags": [],
            "BundleID": 0
        },
        {
            "Address": "interact_interacteffecttable",
            "AssetPath": "Assets/ArtAssets/DATAOUTPUT/interact_interacteffecttable.json",
            "AssetGUID": "",
            "AssetTags": [],
            "BundleID": 0
        },
        {
            "Address": "item_foodtable",
            "AssetPath": "Assets/ArtAssets/DATAOUTPUT/item_foodtable.json",
            "AssetGUID": "",
            "AssetTags": [],
            "BundleID": 0
        },
        {
            "Address": "item_jewelrytable",
            "AssetPath": "Assets/ArtAssets/DATAOUTPUT/item_jewelrytable.json",
            "AssetGUID": "",
            "AssetTags": [],
            "BundleID": 0
        },
        {
            "Address": "item_sceneobjectstable",
            "AssetPath": "Assets/ArtAssets/DATAOUTPUT/item_sceneobjectstable.json",
            "AssetGUID": "",
            "AssetTags": [],
            "BundleID": 0
        },
        {
            "Address": "item_throwobjectstable",
            "AssetPath": "Assets/ArtAssets/DATAOUTPUT/item_throwobjectstable.json",
            "AssetGUID": "",
            "AssetTags": [],
            "BundleID": 0
        },
        {
            "Address": "item_tinyobjectstable",
            "AssetPath": "Assets/ArtAssets/DATAOUTPUT/item_tinyobjectstable.json",
            "AssetGUID": "",
            "AssetTags": [],
            "BundleID": 0
        },
        {
            "Address": "item_toolstable",
            "AssetPath": "Assets/ArtAssets/DATAOUTPUT/item_toolstable.json",
            "AssetGUID": "",
            "AssetTags": [],
            "BundleID": 0
        },
        {
            "Address": "item_weapontable",
            "AssetPath": "Assets/ArtAssets/DATAOUTPUT/item_weapontable.json",
            "AssetGUID": "",
            "AssetTags": [],
            "BundleID": 0
        },
        {
            "Address": "mon_monstertable",
            "AssetPath": "Assets/ArtAssets/DATAOUTPUT/mon_monstertable.json",
            "AssetGUID": "",
            "AssetTags": [],
            "BundleID": 0
        },
        {
            "Address": "scene_doorstable",
            "AssetPath": "Assets/ArtAssets/DATAOUTPUT/scene_doorstable.json",
            "AssetGUID": "",
            "AssetTags": [],
            "BundleID": 0
        },
        {
            "Address": "scene_roomstable",
            "AssetPath": "Assets/ArtAssets/DATAOUTPUT/scene_roomstable.json",
            "AssetGUID": "",
            "AssetTags": [],
            "BundleID": 0
        },
        {
            "Address": "skill_activeskillstable",
            "AssetPath": "Assets/ArtAssets/DATAOUTPUT/skill_activeskillstable.json",
            "AssetGUID": "",
            "AssetTags": [],
            "BundleID": 0
        },
        {
            "Address": "No1",
            "AssetPath": "Assets/ArtAssets/DialogueAsset/No1.asset",
            "AssetGUID": "",
            "AssetTags": [],
            "BundleID": 1
        },
        {
            "Address": "BasketBallTest",
            "AssetPath": "Assets/ArtAssets/Prefabs/Items/Throwable/BasketBallTest.prefab",
            "AssetGUID": "",
            "AssetTags": [],
            "BundleID": 2
        },
        {
            "Address": "WeaponTest",
            "AssetPath": "Assets/ArtAssets/Prefabs/Items/Weapons/WeaponTest.prefab",
            "AssetGUID": "",
            "AssetTags": [],
            "BundleID": 3
        },
        {
            "Address": "Corridor1",
            "AssetPath": "Assets/ArtAssets/Prefabs/Map/Corridor1.prefab",
            "AssetGUID": "",
            "AssetTags": [],
            "BundleID": 4
        },
        {
            "Address": "Door",
            "AssetPath": "Assets/ArtAssets/Prefabs/Map/Door.prefab",
            "AssetGUID": "",
            "AssetTags": [],
            "BundleID": 4
        },
        {
            "Address": "ItemPoint",
            "AssetPath": "Assets/ArtAssets/Prefabs/Map/ItemPoint.prefab",
            "AssetGUID": "",
            "AssetTags": [],
            "BundleID": 4
        },
        {
            "Address": "Map0000",
            "AssetPath": "Assets/ArtAssets/Prefabs/Map/Map0000.prefab",
            "AssetGUID": "",
            "AssetTags": [],
            "BundleID": 4
        },
        {
            "Address": "MonsterPoint",
            "AssetPath": "Assets/ArtAssets/Prefabs/Map/MonsterPoint.prefab",
            "AssetGUID": "",
            "AssetTags": [],
            "BundleID": 4
        },
        {
            "Address": "NavMesh-NavMesh 1",
            "AssetPath": "Assets/ArtAssets/Prefabs/Map/NavMesh-NavMesh 1.asset",
            "AssetGUID": "",
            "AssetTags": [],
            "BundleID": 4
        },
        {
            "Address": "RoomTemplate",
            "AssetPath": "Assets/ArtAssets/Prefabs/Map/RoomTemplate.prefab",
            "AssetGUID": "",
            "AssetTags": [],
            "BundleID": 4
        },
        {
            "Address": "SafetyRoom",
            "AssetPath": "Assets/ArtAssets/Prefabs/Map/SafetyRoom.prefab",
            "AssetGUID": "",
            "AssetTags": [],
            "BundleID": 4
        },
        {
            "Address": "DrownedOnes",
            "AssetPath": "Assets/ArtAssets/Prefabs/NPCs/Monster/DrownedOnes.prefab",
            "AssetGUID": "",
            "AssetTags": [],
            "BundleID": 5
        },
        {
            "Address": "HoundTindalos",
            "AssetPath": "Assets/ArtAssets/Prefabs/NPCs/Monster/HoundTindalos.prefab",
            "AssetGUID": "",
            "AssetTags": [],
            "BundleID": 5
        },
        {
            "Address": "BlueMucus",
            "AssetPath": "Assets/ArtAssets/Prefabs/Object/BlueMucus.prefab",
            "AssetGUID": "",
            "AssetTags": [],
            "BundleID": 6
        },
        {
            "Address": "ZiDan",
            "AssetPath": "Assets/ArtAssets/Prefabs/Object/ZiDan.prefab",
            "AssetGUID": "",
            "AssetTags": [],
            "BundleID": 6
        },
        {
            "Address": "Player000",
            "AssetPath": "Assets/ArtAssets/Prefabs/Player/Player000.prefab",
            "AssetGUID": "",
            "AssetTags": [],
            "BundleID": 7
        },
        {
            "Address": "SwitchButton",
            "AssetPath": "Assets/ArtAssets/Prefabs/UI/HUD/ButtonPrefabs/SwitchButton.prefab",
            "AssetGUID": "",
            "AssetTags": [],
            "BundleID": 8
        },
        {
            "Address": "HUD_GameItemSlotComponent",
            "AssetPath": "Assets/ArtAssets/Prefabs/UI/HUD/HUD_GameItemSlotComponent.prefab",
            "AssetGUID": "",
            "AssetTags": [],
            "BundleID": 9
        },
        {
            "Address": "HUD_MainGameHUD",
            "AssetPath": "Assets/ArtAssets/Prefabs/UI/HUD/HUD_MainGameHUD.prefab",
            "AssetGUID": "",
            "AssetTags": [],
            "BundleID": 9
        },
        {
            "Address": "ItemSlotDock",
            "AssetPath": "Assets/ArtAssets/Prefabs/UI/HUD/HUD_Prefabs/ItemSlotDock.prefab",
            "AssetGUID": "",
            "AssetTags": [],
            "BundleID": 10
        },
        {
            "Address": "MainPanel",
            "AssetPath": "Assets/ArtAssets/Prefabs/UI/MainPanel.prefab",
            "AssetGUID": "",
            "AssetTags": [],
            "BundleID": 11
        },
        {
            "Address": "SaveDataPanel",
            "AssetPath": "Assets/ArtAssets/Prefabs/UI/SaveDataPanel.prefab",
            "AssetGUID": "",
            "AssetTags": [],
            "BundleID": 11
        },
        {
            "Address": "Kira",
            "AssetPath": "Assets/ArtAssets/Sprite/Character/Kira.png",
            "AssetGUID": "",
            "AssetTags": [],
            "BundleID": 12
        },
        {
            "Address": "Natalia",
            "AssetPath": "Assets/ArtAssets/Sprite/Character/Natalia.png",
            "AssetGUID": "",
            "AssetTags": [],
            "BundleID": 12
        },
        {
            "Address": "Flashlight",
            "AssetPath": "Assets/ArtAssets/Sprite/Items/Flashlight.png",
            "AssetGUID": "",
            "AssetTags": [],
            "BundleID": 13
        },
        {
            "Address": "Knife",
            "AssetPath": "Assets/ArtAssets/Sprite/Items/Knife.png",
            "AssetGUID": "",
            "AssetTags": [],
            "BundleID": 13
        },
        {
            "Address": "Bullet",
            "AssetPath": "Assets/ArtAssets/Sprite/Other/Bullet.png",
            "AssetGUID": "",
            "AssetTags": [],
            "BundleID": 14
        },
        {
            "Address": "医务室地板 1200 800",
            "AssetPath": "Assets/ArtAssets/Sprite/Scene/医务室地板 1200 800.png",
            "AssetGUID": "",
            "AssetTags": [],
            "BundleID": 15
        },
        {
            "Address": "医务室长墙面 1200 400",
            "AssetPath": "Assets/ArtAssets/Sprite/Scene/医务室长墙面 1200 400.png",
            "AssetGUID": "",
            "AssetTags": [],
            "BundleID": 15
        },
        {
            "Address": "危险的门 120 200",
            "AssetPath": "Assets/ArtAssets/Sprite/Scene/危险的门 120 200.png",
            "AssetGUID": "",
            "AssetTags": [],
            "BundleID": 15
        },
        {
            "Address": "干净的门 120 200",
            "AssetPath": "Assets/ArtAssets/Sprite/Scene/干净的门 120 200.png",
            "AssetGUID": "",
            "AssetTags": [],
            "BundleID": 15
        },
        {
            "Address": "教室地板 1800 1200",
            "AssetPath": "Assets/ArtAssets/Sprite/Scene/教室地板 1800 1200.png",
            "AssetGUID": "",
            "AssetTags": [],
            "BundleID": 15
        },
        {
            "Address": "教室长墙面 1800 400",
            "AssetPath": "Assets/ArtAssets/Sprite/Scene/教室长墙面 1800 400.png",
            "AssetGUID": "",
            "AssetTags": [],
            "BundleID": 15
        },
        {
            "Address": "素材 医务室单色地砖 灰色",
            "AssetPath": "Assets/ArtAssets/Sprite/Scene/素材 医务室单色地砖 灰色.png",
            "AssetGUID": "",
            "AssetTags": [],
            "BundleID": 15
        },
        {
            "Address": "素材 医务室单色地砖 青色",
            "AssetPath": "Assets/ArtAssets/Sprite/Scene/素材 医务室单色地砖 青色.png",
            "AssetGUID": "",
            "AssetTags": [],
            "BundleID": 15
        },
        {
            "Address": "素材 医务室墙面",
            "AssetPath": "Assets/ArtAssets/Sprite/Scene/素材 医务室墙面.png",
            "AssetGUID": "",
            "AssetTags": [],
            "BundleID": 15
        },
        {
            "Address": "素材 医务室墙面带门",
            "AssetPath": "Assets/ArtAssets/Sprite/Scene/素材 医务室墙面带门.png",
            "AssetGUID": "",
            "AssetTags": [],
            "BundleID": 15
        },
        {
            "Address": "素材 教室地板1",
            "AssetPath": "Assets/ArtAssets/Sprite/Scene/素材 教室地板1.png",
            "AssetGUID": "",
            "AssetTags": [],
            "BundleID": 15
        },
        {
            "Address": "素材 教室地板2",
            "AssetPath": "Assets/ArtAssets/Sprite/Scene/素材 教室地板2.png",
            "AssetGUID": "",
            "AssetTags": [],
            "BundleID": 15
        },
        {
            "Address": "素材 教室墙面",
            "AssetPath": "Assets/ArtAssets/Sprite/Scene/素材 教室墙面.png",
            "AssetGUID": "",
            "AssetTags": [],
            "BundleID": 15
        },
        {
            "Address": "san值",
            "AssetPath": "Assets/ArtAssets/Sprite/UI/Icons/san值.png",
            "AssetGUID": "",
            "AssetTags": [],
            "BundleID": 16
        },
        {
            "Address": "口渴值",
            "AssetPath": "Assets/ArtAssets/Sprite/UI/Icons/口渴值.png",
            "AssetGUID": "",
            "AssetTags": [],
            "BundleID": 16
        },
        {
            "Address": "大圆",
            "AssetPath": "Assets/ArtAssets/Sprite/UI/Icons/大圆.png",
            "AssetGUID": "",
            "AssetTags": [],
            "BundleID": 16
        },
        {
            "Address": "寄生",
            "AssetPath": "Assets/ArtAssets/Sprite/UI/Icons/寄生.png",
            "AssetGUID": "",
            "AssetTags": [],
            "BundleID": 16
        },
        {
            "Address": "弹药",
            "AssetPath": "Assets/ArtAssets/Sprite/UI/Icons/弹药.png",
            "AssetGUID": "",
            "AssetTags": [],
            "BundleID": 16
        },
        {
            "Address": "惊恐",
            "AssetPath": "Assets/ArtAssets/Sprite/UI/Icons/惊恐.png",
            "AssetGUID": "",
            "AssetTags": [],
            "BundleID": 16
        },
        {
            "Address": "椭圆 2",
            "AssetPath": "Assets/ArtAssets/Sprite/UI/Icons/椭圆 2.png",
            "AssetGUID": "",
            "AssetTags": [],
            "BundleID": 16
        },
        {
            "Address": "洞开",
            "AssetPath": "Assets/ArtAssets/Sprite/UI/Icons/洞开.png",
            "AssetGUID": "",
            "AssetTags": [],
            "BundleID": 16
        },
        {
            "Address": "灵视",
            "AssetPath": "Assets/ArtAssets/Sprite/UI/Icons/灵视.png",
            "AssetGUID": "",
            "AssetTags": [],
            "BundleID": 16
        },
        {
            "Address": "状态环",
            "AssetPath": "Assets/ArtAssets/Sprite/UI/Icons/状态环.png",
            "AssetGUID": "",
            "AssetTags": [],
            "BundleID": 16
        },
        {
            "Address": "生命值",
            "AssetPath": "Assets/ArtAssets/Sprite/UI/Icons/生命值.png",
            "AssetGUID": "",
            "AssetTags": [],
            "BundleID": 16
        },
        {
            "Address": "疯狂",
            "AssetPath": "Assets/ArtAssets/Sprite/UI/Icons/疯狂.png",
            "AssetGUID": "",
            "AssetTags": [],
            "BundleID": 16
        },
        {
            "Address": "精准射击",
            "AssetPath": "Assets/ArtAssets/Sprite/UI/Icons/精准射击.png",
            "AssetGUID": "",
            "AssetTags": [],
            "BundleID": 16
        },
        {
            "Address": "美德",
            "AssetPath": "Assets/ArtAssets/Sprite/UI/Icons/美德.png",
            "AssetGUID": "",
            "AssetTags": [],
            "BundleID": 16
        },
        {
            "Address": "飞奔",
            "AssetPath": "Assets/ArtAssets/Sprite/UI/Icons/飞奔.png",
            "AssetGUID": "",
            "AssetTags": [],
            "BundleID": 16
        },
        {
            "Address": "饱腹值",
            "AssetPath": "Assets/ArtAssets/Sprite/UI/Icons/饱腹值.png",
            "AssetGUID": "",
            "AssetTags": [],
            "BundleID": 16
        }
    ],
    "BundleList": [
        {
            "BundleName": "assets_artassets_dataoutput.bundle",
            "UnityCRC": 0,
            "FileHash": "65762c23fb787038360cd24bf6d14c35",
            "FileCRC": "00000000",
            "FileSize": 29614,
            "Encrypted": false,
            "Tags": [],
            "DependIDs": []
        },
        {
            "BundleName": "assets_artassets_dialogueasset.bundle",
            "UnityCRC": 0,
            "FileHash": "07507b99614224b0c164a9d2235cabf9",
            "FileCRC": "00000000",
            "FileSize": 9342,
            "Encrypted": false,
            "Tags": [],
            "DependIDs": []
        },
        {
            "BundleName": "assets_artassets_prefabs_items_throwable.bundle",
            "UnityCRC": 0,
            "FileHash": "c7398e1ddbbec9718b9649684dd0d915",
            "FileCRC": "00000000",
            "FileSize": 4956,
            "Encrypted": false,
            "Tags": [],
            "DependIDs": []
        },
        {
            "BundleName": "assets_artassets_prefabs_items_weapons.bundle",
            "UnityCRC": 0,
            "FileHash": "72aa3ae4d66013dc040c1a4259b84b0b",
            "FileCRC": "00000000",
            "FileSize": 4978,
            "Encrypted": false,
            "Tags": [],
            "DependIDs": []
        },
        {
            "BundleName": "assets_artassets_prefabs_map.bundle",
            "UnityCRC": 0,
            "FileHash": "424b7b852e818e2445b0b5eefee40d8c",
            "FileCRC": "00000000",
            "FileSize": 147604,
            "Encrypted": false,
            "Tags": [],
            "DependIDs": []
        },
        {
            "BundleName": "assets_artassets_prefabs_npcs_monster.bundle",
            "UnityCRC": 0,
            "FileHash": "e80f3d95d49197699477c77b444df24d",
            "FileCRC": "00000000",
            "FileSize": 18609,
            "Encrypted": false,
            "Tags": [],
            "DependIDs": []
        },
        {
            "BundleName": "assets_artassets_prefabs_object.bundle",
            "UnityCRC": 0,
            "FileHash": "f9a2985e3802a2ea530949a082c424f6",
            "FileCRC": "00000000",
            "FileSize": 8508,
            "Encrypted": false,
            "Tags": [],
            "DependIDs": []
        },
        {
            "BundleName": "assets_artassets_prefabs_player.bundle",
            "UnityCRC": 0,
            "FileHash": "7f803001e73f354f794ac2973057604d",
            "FileCRC": "00000000",
            "FileSize": 10440,
            "Encrypted": false,
            "Tags": [],
            "DependIDs": []
        },
        {
            "BundleName": "assets_artassets_prefabs_ui_hud_buttonprefabs.bundle",
            "UnityCRC": 0,
            "FileHash": "257da15453af1c56dbfda7140245ad15",
            "FileCRC": "00000000",
            "FileSize": 7986,
            "Encrypted": false,
            "Tags": [],
            "DependIDs": []
        },
        {
            "BundleName": "assets_artassets_prefabs_ui_hud.bundle",
            "UnityCRC": 0,
            "FileHash": "69c8681ef149cdf4bbae3a7cbc04c9e3",
            "FileCRC": "00000000",
            "FileSize": 33009,
            "Encrypted": false,
            "Tags": [],
            "DependIDs": []
        },
        {
            "BundleName": "assets_artassets_prefabs_ui_hud_hud_prefabs.bundle",
            "UnityCRC": 0,
            "FileHash": "a2cf2f76b324e366bb51871334b4a4ce",
            "FileCRC": "00000000",
            "FileSize": 42555,
            "Encrypted": false,
            "Tags": [],
            "DependIDs": []
        },
        {
            "BundleName": "assets_artassets_prefabs_ui.bundle",
            "UnityCRC": 0,
            "FileHash": "8c784155784c811f682aa9b4d0b44153",
            "FileCRC": "00000000",
            "FileSize": 76673,
            "Encrypted": false,
            "Tags": [],
            "DependIDs": []
        },
        {
            "BundleName": "assets_artassets_sprite_character.bundle",
            "UnityCRC": 0,
            "FileHash": "f210f5da4e2ce649615c4f331933c82d",
            "FileCRC": "00000000",
            "FileSize": 85038,
            "Encrypted": false,
            "Tags": [],
            "DependIDs": []
        },
        {
            "BundleName": "assets_artassets_sprite_items.bundle",
            "UnityCRC": 0,
            "FileHash": "41e4543231c7af699ff6e2ac90a2ae8c",
            "FileCRC": "00000000",
            "FileSize": 9835,
            "Encrypted": false,
            "Tags": [],
            "DependIDs": []
        },
        {
            "BundleName": "assets_artassets_sprite_other.bundle",
            "UnityCRC": 0,
            "FileHash": "223885c0ba54e7ad32477aafa431fb97",
            "FileCRC": "00000000",
            "FileSize": 281,
            "Encrypted": false,
            "Tags": [],
            "DependIDs": []
        },
        {
            "BundleName": "assets_artassets_sprite_scene.bundle",
            "UnityCRC": 0,
            "FileHash": "97922b11c3a843c1c120b4bde50cb985",
            "FileCRC": "00000000",
            "FileSize": 2744556,
            "Encrypted": false,
            "Tags": [],
            "DependIDs": []
        },
        {
            "BundleName": "assets_artassets_sprite_ui_icons.bundle",
            "UnityCRC": 0,
            "FileHash": "7a43a9d0a4d4806164d0d065647f5835",
            "FileCRC": "00000000",
            "FileSize": 286381,
            "Encrypted": false,
            "Tags": [],
            "DependIDs": []
        }
    ]
}