[
  {
    "ID": 920001,
    "NAME": "我的日记？",
    "DESCRIBE": "阿巴阿巴",
    "ImageSpriteName": "Sprite_Inspection_Book"
  },
  {
    "ID": 920002,
    "NAME": "令人不安的纸条",
    "DESCRIBE": " 自指性是文学理论中的一个核心概念，它强调文学语言自身具有表达文学性的能力，这一能力独立于作者的意图、读者的解读和文化背景\n文学作品的审美体验不仅仅来源于作品的内容意义，更重要的是作品形式本身的审美性，如押韵、符号和结构等。\n 文学理论的学习不应仅仅为了掌握某种“真理”，而是为了获得更多的审美视角，丰富文学作品的欣赏和个人的生活经验。\n 文学批评实践中，应平衡对作品形式与内容的关注，既不应过分强调作品的实用性或道德价值，也不应仅关注形式而忽视内容。\n 罗曼·雅各布森的理论提出了文学作品具有诗歌技能或审美技能，即自指性，这一技能是文学作品审美体验的基础。\n 在评价文学作品时，应该注重作品的形式与内容相结合，而不是单一地关注其中之一，以获得更全面的审美体验。\n",
    "ImageSpriteName": "Sprite_Inspection_LargeNote"
  },
  {
    "ID": 920003,
    "NAME": "更令人不安的纸条",
    "DESCRIBE": " 叙事学是一种综合了各种艺术形式的呈现方法，对于任何涉及故事和人物的作品都是不可或缺的。\n 叙述的可靠性取决于叙述者是否参与故事，以及作者是否有意设置矛盾和谎言。\n 叙述者与读者之间的关系复杂多变，包括真实作者、隐含作者、叙述者以及真实读者、隐含读者和受书者等多个层面。\n 视角和声音是叙事中的关键元素，它们可以独立变化，影响故事的呈现方式和读者的感受。\n 时序、节奏和频率是叙事的基本组成部分，它们共同决定了故事的张力、节奏和情感深度。\n 叙事学在文学评论中具有重要价值，但应避免过度使用理论术语，以免失去对作品本身的直观感受和理解。",
    "ImageSpriteName": "Sprite_Inspection_LittleNote"
  },
  {
    "ID": 920004,
    "NAME": "不知是谁留下的刻字",
    "DESCRIBE": "啊啊啊！——\n就这个feel倍儿爽！\n     哼哼嗯啊啊啊啊啊\n哦~哦~哦~哦哦~     我报赣南师大~\n",
    "ImageSpriteName": "Sprite_Inspection_Inscription"
  },
  {
    "ID": 920005,
    "NAME": "策划的备忘",
    "DESCRIBE": "打开检视界面时\n典藏版：用统一的音效\n豪华版：每类物品单独配一个查看音效，且不同角色在检视界面的文本略有差异",
    "ImageSpriteName": "Sprite_Inspection_Note"
  }
]